<?xml version="1.0" encoding="utf-8"?>
<odoo>
    <data>
        <!-- Menu racine -->
        <menuitem id="pointeur_hr_menu_root"
                  name="Pointeur HR"
                  sequence="80"/>

        <!-- Sous-menu Présences -->
        <menuitem id="pointeur_hr_menu_attendance"
                  name="Présences"
                  parent="pointeur_hr_menu_root"
                  sequence="10"/>

        <!-- Sous-menu Configuration -->
        <menuitem id="pointeur_hr_menu_config"
                  name="Configuration"
                  parent="pointeur_hr_menu_root"
                  sequence="100"/>

        <!-- Sous-menu Reporting -->
        <menuitem id="pointeur_hr_menu_reporting"
                  name="Reporting"
                  parent="pointeur_hr_menu_root"
                  sequence="90"/>

        <!-- Menu Rapport de présence -->
        <menuitem id="pointeur_hr_menu_attendance_report"
                  name="Rapport de présence"
                  parent="pointeur_hr_menu_reporting"
                  action="pointeur_hr_action_hr_attendance_report"
                  sequence="10"/>

        <!-- Menu Lieux de pointage -->
        <menuitem id="pointeur_hr_menu_location"
                  name="Lieux de pointage"
                  parent="pointeur_hr_menu_config"
                  action="pointeur_hr_action_location"
                  sequence="10"/>

        <!-- Menu Import des pointages -->
        <menuitem id="pointeur_hr_menu_import"
                  name="Import des pointages"
                  parent="pointeur_hr_menu_attendance"
                  action="pointeur_hr_action_import"
                  sequence="10"/>
    </data>
</odoo>
